{
    "version": 2,
    "cmakeMinimumRequired": {
        "major": 3,
        "minor": 20,
        "patch": 0
    },
    "configurePresets": [
        {
            "name": "001_NewBranch",
            "displayName": "001_NewBranch",
            "description": "001_NewBranch",
            "generator": "Ninja",
            "binaryDir": "${sourceDir}/build/${presetName}",
            "cacheVariables": {
                "CMAKE_BUILD_TYPE": "Debug",
                "CMAKE_INSTALL_PREFIX": "${sourceDir}/install/${presetName}",
                "CMAKE_TOOLCHAIN_FILE": "./cmake/gcc_cortexM7.cmake",
                "BOARD_TYPE": "prototype_b",
                "HW_UNIT_TESTS": "ON"
            }
        }
    ],
    "buildPresets": [
        {
            "name": "001_NewBranch",
            "configurePreset": "001_NewBranch"
        }
    ]
}
